postgreslite/__init__.py
postgreslite/handler.py
postgreslite/pool.py
postgreslite-0.2.0.dist-info/licenses/LICENSE
postgreslite-0.2.0.dist-info/METADATA
postgreslite-0.2.0.dist-info/WHEEL
postgreslite-0.2.0.dist-info/top_level.txt
postgreslite-0.2.0.dist-info/RECORD
